botiverse/__init__.py
botiverse/Theorizer/Theorizer.py
botiverse/Theorizer/__init__.py
botiverse/Theorizer/constants.py
botiverse/Theorizer/generate.py
botiverse/Theorizer/model/__init__.py
botiverse/Theorizer/model/dataloader.py
botiverse/Theorizer/model/finetuned_model.py
botiverse/Theorizer/model/train.py
botiverse/Theorizer/model/utils.py
botiverse/Theorizer/squad/__init__.py
botiverse/Theorizer/squad/function_words.txt
botiverse/Theorizer/squad/info_extractor.py
botiverse/Theorizer/squad/sample_data.py
botiverse/Theorizer/squad/squad_example.py
botiverse/Theorizer/squad/utils.py
botiverse/bots/__init__.py
botiverse/bots/BasicBot/BasicBot.py
botiverse/bots/BasicBot/__init__.py
botiverse/bots/BasicTaskBot/BasicTaskBot.py
botiverse/bots/BasicTaskBot/__init__.py
botiverse/bots/BasicTaskBot/utils.py
botiverse/bots/ConverseBot/ConverseBot.py
botiverse/bots/ConverseBot/__init__.py
botiverse/bots/TaskBot/TaskBot.py
botiverse/bots/TaskBot/__init__.py
botiverse/bots/TaskBot/utils.py
botiverse/bots/VoiceBot/SpeechClassifier.py
botiverse/bots/VoiceBot/VoiceBot.py
botiverse/bots/VoiceBot/__init__.py
botiverse/bots/VoiceBot/utils.py
botiverse/bots/WhizBot/WhizBot.py
botiverse/bots/WhizBot/WhizBot_BERT.py
botiverse/bots/WhizBot/WhizBot_GRU.py
botiverse/bots/WhizBot/__init__.py
botiverse/gui/__init__.py
botiverse/gui/gui.py
botiverse/gui/static/favicon.png
botiverse/gui/static/logo.png
botiverse/gui/static/style.css
botiverse/gui/static/icons/Basic Bot.png
botiverse/gui/static/icons/Converse Bot.png
botiverse/gui/static/icons/Task Bot.png
botiverse/gui/static/icons/Theorizer.png
botiverse/gui/static/icons/Voice Bot.png
botiverse/gui/static/icons/Whiz Bot.png
botiverse/gui/templates/chat.html
botiverse/models/__init__.py
botiverse/models/BERT/BERT.py
botiverse/models/BERT/__init__.py
botiverse/models/BERT/config.py
botiverse/models/BERT/utils.py
botiverse/models/FastSpeech1/FastSpeech.py
botiverse/models/FastSpeech1/__init__.py
botiverse/models/GRUClassifier/GRUClassifier.py
botiverse-0.5.1.dist-info/METADATA
botiverse-0.5.1.dist-info/WHEEL
botiverse-0.5.1.dist-info/top_level.txt
botiverse-0.5.1.dist-info/RECORD
